olivia_dataset/__init__.py
olivia_dataset/bin/__init__.py
olivia_dataset/bin/olivia_dataset_config.py
olivia_dataset/bin/olivia_dataset_refresh.py
olivia_dataset/fetching/__init__.py
olivia_dataset/fetching/cdc/__init__.py
olivia_dataset/fetching/cdc/covid19_hospitalizations.py
olivia_dataset/fetching/covid19_outcomes/__init__.py
olivia_dataset/fetching/covid19_outcomes/point3acres.py
olivia_dataset/preprocessing/__init__.py
olivia_dataset/utilities/__init__.py
olivia_dataset/utilities/config.py
olivia_dataset/utilities/web/__init__.py
olivia_dataset/utilities/web/download.py
olivia_dataset-1.0.0.data/scripts/olivia_dataset_config
olivia_dataset-1.0.0.data/scripts/olivia_dataset_refresh
olivia_dataset-1.0.0.dist-info/METADATA
olivia_dataset-1.0.0.dist-info/WHEEL
olivia_dataset-1.0.0.dist-info/top_level.txt
olivia_dataset-1.0.0.dist-info/RECORD
